{
    "kind": "collectionType",
    "collectionName": "order_items",
    "info": {
        "singularName": "order-item",
        "pluralName": "order-items",
        "displayName": "order_item"
    },
    "options": {
        "draftAndPublish": true
    },
    "attributes": {
        "quantity": {
            "type": "integer"
        },
        "price": {
            "type": "integer"
        },
        "item_variant": {
            "type": "relation",
            "relation": "manyToOne",
            "target": "api::item-variant.item-variant"
        },
        "order": {
            "type": "relation",
            "relation": "manyToOne",
            "target": "api::order.order",
            "inversedBy": "order_items"
        }
    }
}
